<?xml version="1.0" encoding="utf-8"?><annotation>  
	  <folder>bird_train</folder>  
	  <filename>Black_Footed_Albatross_0038_212.jpg</filename>  
	  <path>CUB_200_2011/images/001.Black_footed_Albatross/Black_Footed_Albatross_0038_212.jpg</path>  
	  <source>    
		    <database>Unknown</database>    
	  </source>  
	  <size>    
		    <width>500</width>    
		    <height>332</height>    
		    <depth>3</depth>    
	  </size>  
	  <segmented>0</segmented>  
	  <object>    
		    <name>Black_footed_Albatross</name>    
		    <pose>Unspecified</pose>    
		    <truncated>0</truncated>    
		    <difficult>0</difficult>    
		    <bndbox>      
			      <xmin>137</xmin>      
			      <ymin>64</ymin>      
			      <xmax>424</xmax>      
			      <ymax>220</ymax>      
		    </bndbox>    
	  </object>  
</annotation>